{
  "1-1-1": "keep-keep-keep",
  "2-1-1": "keep-keep-keep",
  "2-2-1": "roll-roll-keep",
  "2-2-2": "keep-keep-keep",
  "3-1-1": "keep-keep-keep",
  "3-2-1": "roll-roll-keep",
  "3-2-2": "roll-roll-roll",
  "3-3-1": "roll-roll-keep",
  "3-3-2": "roll-roll-roll",
  "3-3-3": "keep-keep-keep",
  "4-1-1": "keep-keep-keep",
  "4-2-1": "keep-keep-keep",
  "4-2-2": "keep-roll-roll",
  "4-3-1": "keep-roll-keep",
  "4-3-2": "keep-roll-keep",
  "4-3-3": "roll-roll-roll",
  "4-4-1": "roll-keep-keep",
  "4-4-2": "roll-keep-keep",
  "4-4-3": "keep-roll-roll",
  "4-4-4": "keep-keep-keep",
  "5-1-1": "keep-keep-keep",
  "5-2-1": "roll-keep-keep",
  "5-2-2": "roll-roll-roll",
  "5-3-1": "roll-roll-keep",
  "5-3-2": "roll-roll-roll",
  "5-3-3": "roll-keep-keep",
  "5-4-1": "roll-keep-keep",
  "5-4-2": "roll-keep-keep",
  "5-4-3": "keep-keep-keep",
  "5-4-4": "roll-roll-keep",
  "5-5-1": "roll-roll-keep",
  "5-5-2": "roll-roll-roll",
  "5-5-3": "roll-roll-roll",
  "5-5-4": "roll-roll-keep",
  "5-5-5": "keep-keep-keep",
  "6-1-1": "keep-keep-keep",
  "6-2-1": "roll-roll-keep",
  "6-2-2": "roll-roll-keep",
  "6-3-1": "roll-roll-keep",
  "6-3-2": "roll-roll-roll",
  "6-3-3": "roll-roll-roll",
  "6-4-1": "roll-keep-keep",
  "6-4-2": "roll-keep-roll",
  "6-4-3": "roll-roll-roll",
  "6-4-4": "roll-roll-keep",
  "6-5-1": "roll-roll-keep",
  "6-5-2": "roll-roll-keep",
  "6-5-3": "roll-roll-roll",
  "6-5-4": "roll-roll-keep",
  "6-5-5": "roll-roll-roll",
  "6-6-1": "roll-roll-keep",
  "6-6-2": "roll-roll-keep",
  "6-6-3": "roll-roll-roll",
  "6-6-4": "roll-roll-keep",
  "6-6-5": "roll-roll-roll",
  "6-6-6": "keep-keep-keep"
}